<?xml version="1.0" encoding="UTF-8"?>
<objects serializationModel="Studio.02.00.00">
	<object class="Event" id="{6921ef2a-356b-45fe-a1a8-ea3d635531d6}">
		<property name="name">
			<value>tiaoyue1</value>
		</property>
		<property name="outputFormat">
			<value>1</value>
		</property>
		<relationship name="folder">
			<destination>{4c86fc44-4275-474f-ad15-0e01468f3407}</destination>
		</relationship>
		<relationship name="mixer">
			<destination>{77e23086-d4dc-4ddc-80ca-802f3188d95b}</destination>
		</relationship>
		<relationship name="masterTrack">
			<destination>{819d9689-b62d-4da5-b36a-4f529018e449}</destination>
		</relationship>
		<relationship name="mixerInput">
			<destination>{a6b6ae39-bd1c-41bd-98b2-bd01317aca16}</destination>
		</relationship>
		<relationship name="automatableProperties">
			<destination>{04cdfb71-cb0d-457a-9a6d-4c999791b347}</destination>
		</relationship>
		<relationship name="markerTracks">
			<destination>{a6f0067e-ae80-4b15-a632-187634ca3c55}</destination>
		</relationship>
		<relationship name="groupTracks">
			<destination>{0ff7ca6b-b013-45ff-8e37-8edd64632986}</destination>
		</relationship>
		<relationship name="timeline">
			<destination>{0655b68a-f79a-4483-b34a-eedb45ecaa45}</destination>
		</relationship>
		<relationship name="banks">
			<destination>{4fef3b80-cd5a-4053-92bb-270c45d67aa0}</destination>
		</relationship>
	</object>
	<object class="EventMixer" id="{77e23086-d4dc-4ddc-80ca-802f3188d95b}">
		<relationship name="masterBus">
			<destination>{6931b48b-efcd-4f6b-a6a0-5bc2e7765106}</destination>
		</relationship>
	</object>
	<object class="MasterTrack" id="{819d9689-b62d-4da5-b36a-4f529018e449}">
		<relationship name="mixerGroup">
			<destination>{6931b48b-efcd-4f6b-a6a0-5bc2e7765106}</destination>
		</relationship>
	</object>
	<object class="MixerInput" id="{a6b6ae39-bd1c-41bd-98b2-bd01317aca16}">
		<relationship name="effectChain">
			<destination>{eddfdf2d-9a87-40ce-840e-7589f06eb12a}</destination>
		</relationship>
		<relationship name="panner">
			<destination>{9ee7007f-0402-4e77-9ca8-1f10e5633d60}</destination>
		</relationship>
		<relationship name="output">
			<destination>{c9d79681-1fa5-4a7d-9043-fa8ac1af89de}</destination>
		</relationship>
	</object>
	<object class="EventAutomatableProperties" id="{04cdfb71-cb0d-457a-9a6d-4c999791b347}" />
	<object class="MarkerTrack" id="{a6f0067e-ae80-4b15-a632-187634ca3c55}" />
	<object class="GroupTrack" id="{0ff7ca6b-b013-45ff-8e37-8edd64632986}">
		<relationship name="modules">
			<destination>{331621c7-498a-48bc-bcad-5e8407701b16}</destination>
		</relationship>
		<relationship name="mixerGroup">
			<destination>{ffbf08ce-2c35-468e-a99b-9633bb9585f8}</destination>
		</relationship>
	</object>
	<object class="Timeline" id="{0655b68a-f79a-4483-b34a-eedb45ecaa45}">
		<relationship name="modules">
			<destination>{331621c7-498a-48bc-bcad-5e8407701b16}</destination>
		</relationship>
	</object>
	<object class="EventMixerMaster" id="{6931b48b-efcd-4f6b-a6a0-5bc2e7765106}">
		<relationship name="effectChain">
			<destination>{df4c2711-3d01-47cb-8fec-0f4ac9639392}</destination>
		</relationship>
		<relationship name="panner">
			<destination>{431b2e6f-00ce-4c9e-abc9-4ec620c72f45}</destination>
		</relationship>
		<relationship name="mixer">
			<destination>{77e23086-d4dc-4ddc-80ca-802f3188d95b}</destination>
		</relationship>
	</object>
	<object class="MixerBusEffectChain" id="{eddfdf2d-9a87-40ce-840e-7589f06eb12a}">
		<relationship name="effects">
			<destination>{bce4c962-064a-4730-8586-64380a74435c}</destination>
		</relationship>
	</object>
	<object class="MixerBusPanner" id="{9ee7007f-0402-4e77-9ca8-1f10e5633d60}" />
	<object class="SingleSound" id="{331621c7-498a-48bc-bcad-5e8407701b16}">
		<property name="length">
			<value>0.039949999999999999</value>
		</property>
		<property name="timelockedOffset">
			<value>0.25550000000000006</value>
		</property>
		<property name="volume">
			<value>10</value>
		</property>
		<relationship name="modulators">
			<destination>{e91d439c-591e-4ae3-a465-14398bb27ae9}</destination>
		</relationship>
		<relationship name="audioFile">
			<destination>{23976ce1-ae87-4221-b2e9-28e9d7b32b1d}</destination>
		</relationship>
	</object>
	<object class="EventMixerGroup" id="{ffbf08ce-2c35-468e-a99b-9633bb9585f8}">
		<property name="volume">
			<value>10</value>
		</property>
		<property name="name">
			<value>Audio 1</value>
		</property>
		<relationship name="effectChain">
			<destination>{efaaa6d5-e782-45a0-8c6c-f0e2b6e31716}</destination>
		</relationship>
		<relationship name="panner">
			<destination>{e59cb0c9-acf2-4705-ad28-31ff690a4055}</destination>
		</relationship>
		<relationship name="output">
			<destination>{6931b48b-efcd-4f6b-a6a0-5bc2e7765106}</destination>
		</relationship>
	</object>
	<object class="MixerBusEffectChain" id="{df4c2711-3d01-47cb-8fec-0f4ac9639392}">
		<relationship name="effects">
			<destination>{89b31408-6527-4af2-8005-c537b7ae5af8}</destination>
		</relationship>
	</object>
	<object class="MixerBusPanner" id="{431b2e6f-00ce-4c9e-abc9-4ec620c72f45}" />
	<object class="MixerBusFader" id="{bce4c962-064a-4730-8586-64380a74435c}" />
	<object class="RandomizerModulator" id="{e91d439c-591e-4ae3-a465-14398bb27ae9}">
		<property name="nameOfPropertyBeingModulated">
			<value>volume</value>
		</property>
		<property name="amount">
			<value>19.5</value>
		</property>
	</object>
	<object class="MixerBusEffectChain" id="{efaaa6d5-e782-45a0-8c6c-f0e2b6e31716}">
		<relationship name="effects">
			<destination>{166cb92d-61a8-4059-9df9-f2e5933c0416}</destination>
		</relationship>
	</object>
	<object class="MixerBusPanner" id="{e59cb0c9-acf2-4705-ad28-31ff690a4055}" />
	<object class="MixerBusFader" id="{89b31408-6527-4af2-8005-c537b7ae5af8}" />
	<object class="MixerBusFader" id="{166cb92d-61a8-4059-9df9-f2e5933c0416}" />
</objects>
